bot/broker.py
bot/disk.py
bot/error.py
bot/find.py
bot/object.py
bot/run.py
bot/thread.py
bot/modules/__init__.py
bot/modules/cmd.py
bot/modules/fnd.py
bot/modules/irc.py
bot/modules/log.py
bot/modules/mod.py
bot/modules/rss.py
bot/modules/sts.py
bot/modules/tdo.py
bot/modules/thr.py
libbot-44.data/data/share/doc/libbot/README.rst
libbot-44.data/data/share/libbot/mods/__init__.py
libbot-44.data/data/share/libbot/mods/mbx.py
libbot-44.data/data/share/libbot/mods/mdl.py
libbot-44.data/data/share/libbot/mods/req.py
libbot-44.data/data/share/libbot/mods/shp.py
libbot-44.data/data/share/libbot/mods/udp.py
libbot-44.data/data/share/libbot/mods/wsd.py
libbot-44.data/data/share/libbot/mods/wsh.py
libbot-44.data/scripts/bot
libbot-44.dist-info/METADATA
libbot-44.dist-info/WHEEL
libbot-44.dist-info/top_level.txt
libbot-44.dist-info/zip-safe
libbot-44.dist-info/RECORD
