Metadata-Version: 2.1
Name: libbot
Version: 44
Summary: the python3 bot namespace
Author-email: libbot <libbotx@gmail.com>
License: Public Domain
Project-URL: home, https://pypi.org/project/libbot
Project-URL: bugs, https://github.com/botlibx/libbot/issues
Project-URL: source, https://github.com/botlibx/libbot
Classifier: Development Status :: 3 - Alpha
Classifier: License :: Public Domain
Classifier: Operating System :: Unix
Classifier: Programming Language :: Python
Classifier: Topic :: Utilities
